hyperlpr3/__init__.py
hyperlpr3/hyperlpr3.py
hyperlpr3/command/__init__.py
hyperlpr3/command/aliased_group.py
hyperlpr3/command/cli.py
hyperlpr3/command/sample.py
hyperlpr3/command/serve.py
hyperlpr3/common/__init__.py
hyperlpr3/common/mnn_adapt.py
hyperlpr3/common/tokenize.py
hyperlpr3/common/tools_process.py
hyperlpr3/common/typedef.py
hyperlpr3/config/__init__.py
hyperlpr3/config/configuration.py
hyperlpr3/config/settings.py
hyperlpr3/inference/__init__.py
hyperlpr3/inference/classification.py
hyperlpr3/inference/detect.py
hyperlpr3/inference/multitask_detect.py
hyperlpr3/inference/pipeline.py
hyperlpr3/inference/recognition.py
hyperlpr3/inference/vertex.py
hyperlpr3/inference/base/__init__.py
hyperlpr3/inference/base/base.py
hyperlpr3-0.1.2.dist-info/METADATA
hyperlpr3-0.1.2.dist-info/WHEEL
hyperlpr3-0.1.2.dist-info/entry_points.txt
hyperlpr3-0.1.2.dist-info/top_level.txt
hyperlpr3-0.1.2.dist-info/RECORD
